anbiopy/__init__.py
anbiopy/methods.py
anbiopy-0.1.3.dist-info/METADATA
anbiopy-0.1.3.dist-info/WHEEL
anbiopy-0.1.3.dist-info/licenses/LICENSE
anbiopy-0.1.3.dist-info/RECORD
