Metadata-Version: 2.4
Name: anbiopy
Version: 0.1.3
Summary: Python package designed for the analysis of microbiota data when incorporating other types of variables e.g., anthropometric
Project-URL: Homepage, https://github.com/juanspardor/anbiopy
Project-URL: Issues, https://github.com/juanspardor/anbiopy/issues
Author-email: Juan Sebastian Pardo <j.pardor@uniandes.edu.co>
License-Expression: MIT
License-File: LICENSE
Classifier: Operating System :: OS Independent
Classifier: Programming Language :: Python :: 3
Requires-Python: >=3.8
Requires-Dist: matplotlib
Requires-Dist: numpy
Requires-Dist: pandas
Requires-Dist: scikit-bio
Requires-Dist: scikit-learn
Requires-Dist: scipy
Requires-Dist: seaborn
Requires-Dist: statsmodels
